32micro.v
module micro32 (clk1, clk2);
    
    input clk1, clk2;               //Two-Phase Clock

    reg [31:0] PC, IF_ID_IR, IF_ID_NPC;
    reg [31:0] ID_EX_IR, ID_EX_NPC, ID_EX_A, ID_EX_B, ID_EX_Imm;
    reg [2:0]  ID_EX_type, EX_MEM_type, MEM_WB_type;
    reg [31:0] EX_MEM_IR, EX_MEM_ALUOut, EX_MEM_B;
    reg        EX_MEM_cond;
    reg [31:0] MEM_WB_IR, MEM_WB_ALUOut, MEM_WB_LMD;

    reg [31:0] Reg [0:31];          //Register Bank (32 X 32)
    reg [31:0] Mem [0:1023];        //1024 X 32 Memory

    parameter ADD=6'b000000, SUB=6'b000001, AND=6'b000010, OR=6'b000011, SLT=6'b000100;
    parameter MUL=6'b000101, HLT=6'b111111,LW=6'b001000, SW=6'b00101, ADDI=6'b001010;
    parameter SUBI=6'b001011, SLTI=6'b001100, BNEQZ=6'b001101, BEQZ=6'b001110;

    parameter RR_ALU=3'b000, RM_ALU=3'b001, LOAD=3'b010, STORE=3'b011;
    parameter BRANCH=3'b100, HALT=3'b101;

    reg HALTED;                    
        //Set after HLT instruction is completed (WB Stage)
    reg TAKEN_BRANCH;
        // Required to disable instructions after branch

    always @(posedge clk1 )          //***IF Stage***
        if(HALTED==0)
        begin
           if(((EX_MEM_IR[31:26] == BEQZ)&&(EX_MEM_cond==1)) || ((EX_MEM_IR[31:26] == BNEQZ)&& (EX_MEM_cond ==0)))
           begin
            IF_ID_IR <= #2 Mem[EX_MEM_ALUOut];
            TAKEN_BRANCH <= #2 1'b1;
            IF_ID_NPC <= #2 EX_MEM_ALUOut+1;
            PC <= #2 EX_MEM_ALUOut+1;
           end
           else
            begin
                IF_ID_IR <= #2 Mem[PC];
                IF_ID_NPC <= #2 PC+1;
                PC <= #2 PC+1;
            end    
        end    

    always @(posedge clk2)          //ID Stage
        if (HALTED==0)
        begin
            if(IF_ID_IR[25:21]==5'b00000) ID_EX_A <= #2 0;  // rs
            else ID_EX_A <= #2 Reg[IF_ID_IR[25:21]];   

            if(IF_ID_IR[20:16]==5'b00000) ID_EX_B <= #2 0;  // rt
            else ID_EX_B <= #2 Reg[IF_ID_IR[20:16]];   

            ID_EX_NPC <= #2 IF_ID_NPC;
            ID_EX_IR  <= #2 IF_ID_IR;
            ID_EX_Imm <= #2 {{16{IF_ID_IR[15]}}, {IF_ID_IR[15:0]}};

            case( IF_ID_IR[31:26])
              ADD,SUB,MUL,AND,OR,SLT: ID_EX_type <= #2 RR_ALU;
              ADDI,SUBI,SLTI:         ID_EX_type <= #2 RM_ALU;
              LW:                     ID_EX_type <= #2 LOAD;
              SW:                     ID_EX_type <= #2 STORE;
              BNEQZ,BEQZ:             ID_EX_type <= #2 BRANCH;
              HLT:                    ID_EX_type <= #2 HALT;
              default:                ID_EX_type <= #2 HALT;     //Inavlid Operation
            endcase
        end
 
    always @(posedge clk1)              // EX Stage
        if(HALTED==0)
        begin
            EX_MEM_type <= #2 ID_EX_type;
            EX_MEM_IR   <= #2 ID_EX_IR;
            TAKEN_BRANCH<= #2 0;

            case (ID_EX_type)
              RR_ALU: begin
                        case(ID_EX_IR[31:26])
                          ADD:   EX_MEM_ALUOut <= #2 ID_EX_A + ID_EX_B;
                          SUB:   EX_MEM_ALUOut <= #2 ID_EX_A - ID_EX_B;
                          MUL:   EX_MEM_ALUOut <= #2 ID_EX_A * ID_EX_B;
                          OR :   EX_MEM_ALUOut <= #2 ID_EX_A | ID_EX_B;
                          AND:   EX_MEM_ALUOut <= #2 ID_EX_A & ID_EX_B;
                          SLT:   EX_MEM_ALUOut <= #2 ID_EX_A < ID_EX_B;
                          default:   EX_MEM_ALUOut <= #2 32'hxxxxxxxx;
                        endcase
                       end   

              RM_ALU:  begin
                         case(ID_EX_IR[31:26])
                           ADDI:   EX_MEM_ALUOut <= #2 ID_EX_A + ID_EX_Imm;
                           SUBI:   EX_MEM_ALUOut <= #2 ID_EX_A - ID_EX_Imm;
                           SLTI:   EX_MEM_ALUOut <= #2 ID_EX_A < ID_EX_Imm;
                           default:   EX_MEM_ALUOut <= #2 32'hxxxxxxxx;
                         endcase
                       end

              LOAD, STORE:  begin
                             EX_MEM_ALUOut <= #2 ID_EX_A + ID_EX_Imm;
                             EX_MEM_B      <= #2 ID_EX_B;
                            end

               BRANCH: begin
                        EX_MEM_ALUOut <= #2 ID_EX_NPC + ID_EX_Imm;               
                        EX_MEM_cond   <= #2 (ID_EX_A==0);
                       end
            endcase
        end   

    always @(posedge clk2)                        //MEM Stage
        if(HALTED==0)
        begin
          MEM_WB_type <= #2 EX_MEM_type;
          MEM_WB_IR   <= #2 EX_MEM_IR;

        case(EX_MEM_type)
            RR_ALU, RM_ALU:
                     MEM_WB_ALUOut <= #2 EX_MEM_ALUOut;
            
            LOAD:    MEM_WB_LMD    <= #2 Mem[EX_MEM_ALUOut]; 

            STORE:  if(TAKEN_BRANCH == 0)        //Disable Write    
                      Mem[EX_MEM_ALUOut] <= #2 EX_MEM_B;

        endcase           
        end  

    always @(posedge clk1)              // WB Stage
        begin
        if(TAKEN_BRANCH == 0)           // Disable Write if branch taken 
           case(MEM_WB_type)
           RR_ALU:   Reg[MEM_WB_IR[15:11]] <= #2 MEM_WB_ALUOut;    // "rd"
           RM_ALU:   Reg[MEM_WB_IR[20:16]] <= #2 MEM_WB_ALUOut;    // "rt"
           
           LOAD:     Reg[MEM_WB_IR[20:16]] <= #2 MEM_WB_LMD;       // "rt"
           HALT:     HALTED <= #2 1'b1;
           endcase
        end    

endmodule

32micro_tb2.v
module micro32_tb2;

reg clk1 , clk2;
integer k;

micro32 mips2 (clk1, clk2);

initial begin
   clk1=0; clk2=0;
    repeat(50)
   begin
    #5 clk1=1; #5 clk1=0;
    #5 clk2=1; #5 clk2=0;
   end
end

initial
    begin
        for(k=0; k<31; k=k+1)
          mips2.Reg[k]=k;

        mips2.Mem[0] = 32'h28010078;      //ADDI R1,R0,120
        mips2.Mem[1] = 32'h0c631800;      //OR R3,R3,R3 --- DUMMY INSTR.
        mips2.Mem[2] = 32'h20220000;      //LW R2,0(R1)
        mips2.Mem[3] = 32'h0c631800;      //OR R3,R3,R3 --- DUMMY INSTR.
        mips2.Mem[4] = 32'h2842002d;      //ADDI R2,R2,45
        mips2.Mem[5] = 32'h0c631800;      //OR R3,R3,R3 --- DUMMY INSTR.
        mips2.Mem[6] = 32'h24220001;      //SW R2,1(R1)
        mips2.Mem[7] = 32'hfc000000;      //HLT

        mips2.Mem[120] = 85;

        mips2.HALTED=0;
        mips2.PC=0;
        mips2.TAKEN_BRANCH=0;

        #500 $display("Mem[120] : %4d \nMem[121] : %4d", mips2.Mem[120], mips2.Mem[121]);
    end
initial
    begin
        $dumpfile ("micro32_tb2.vcd");
        $dumpvars (0,micro32_tb2);
        #600 $finish;
    end


endmodule

micro32_tb2.vcd
$date
	Tue Jun 24 00:16:47 2025
$end
$version
	Icarus Verilog
$end
$timescale
	1s
$end
$scope module micro32_tb2 $end
$var reg 1 ! clk1 $end
$var reg 1 " clk2 $end
$var integer 32 # k [31:0] $end
$scope module mips2 $end
$var wire 1 $ clk1 $end
$var wire 1 % clk2 $end
$var reg 32 & EX_MEM_ALUOut [31:0] $end
$var reg 32 ' EX_MEM_B [31:0] $end
$var reg 32 ( EX_MEM_IR [31:0] $end
$var reg 1 ) EX_MEM_cond $end
$var reg 3 * EX_MEM_type [2:0] $end
$var reg 1 + HALTED $end
$var reg 32 , ID_EX_A [31:0] $end
$var reg 32 - ID_EX_B [31:0] $end
$var reg 32 . ID_EX_IR [31:0] $end
$var reg 32 / ID_EX_Imm [31:0] $end
$var reg 32 0 ID_EX_NPC [31:0] $end
$var reg 3 1 ID_EX_type [2:0] $end
$var reg 32 2 IF_ID_IR [31:0] $end
$var reg 32 3 IF_ID_NPC [31:0] $end
$var reg 32 4 MEM_WB_ALUOut [31:0] $end
$var reg 32 5 MEM_WB_IR [31:0] $end
$var reg 32 6 MEM_WB_LMD [31:0] $end
$var reg 3 7 MEM_WB_type [2:0] $end
$var reg 32 8 PC [31:0] $end
$var reg 1 9 TAKEN_BRANCH $end
$upscope $end
$upscope $end
$enddefinitions $end
#0
$dumpvars
09
b0 8
bx 7
bx 6
bx 5
bx 4
bx 3
bx 2
bx 1
bx 0
bx /
bx .
bx -
bx ,
0+
bx *
x)
bx (
bx '
bx &
0%
0$
b11111 #
0"
0!
$end
#5
1!
1$
#7
b1 8
b1 3
b101000000000010000000001111000 2
#10
0!
0$
#15
1"
1%
#17
b1 1
b1111000 /
b101000000000010000000001111000 .
b1 0
b1 -
b0 ,
#20
0"
0%
#25
1!
1$
#27
b1111000 &
b101000000000010000000001111000 (
b1 *
b10 8
b10 3
b1100011000110001100000000000 2
#30
0!
0$
#35
1"
1%
#37
b1111000 4
b101000000000010000000001111000 5
b1 7
b0 1
b1100000000000 /
b1100011000110001100000000000 .
b10 0
b11 -
b11 ,
#40
0"
0%
#45
1!
1$
#47
b11 8
b11 3
b100000001000100000000000000000 2
b11 &
b1100011000110001100000000000 (
b0 *
#50
0!
0$
#55
1"
1%
#57
b10 1
b0 /
b100000001000100000000000000000 .
b11 0
b10 -
b1111000 ,
b11 4
b1100011000110001100000000000 5
b0 7
#60
0"
0%
#65
1!
1$
#67
b10 '
b1111000 &
b100000001000100000000000000000 (
b10 *
b100 8
b100 3
b1100011000110001100000000000 2
#70
0!
0$
#75
1"
1%
#77
b1010101 6
b100000001000100000000000000000 5
b10 7
b0 1
b1100000000000 /
b1100011000110001100000000000 .
b100 0
b11 -
b11 ,
#80
0"
0%
#85
1!
1$
#87
b101 8
b101 3
b101000010000100000000000101101 2
b11 &
b1100011000110001100000000000 (
b0 *
#90
0!
0$
#95
1"
1%
#97
b1 1
b101101 /
b101000010000100000000000101101 .
b101 0
b1010101 -
b1010101 ,
b1100011000110001100000000000 5
b0 7
#100
0"
0%
#105
1!
1$
#107
b10000010 &
b101000010000100000000000101101 (
b1 *
b110 8
b110 3
b1100011000110001100000000000 2
#110
0!
0$
#115
1"
1%
#117
b10000010 4
b101000010000100000000000101101 5
b1 7
b0 1
b1100000000000 /
b1100011000110001100000000000 .
b110 0
b11 -
b11 ,
#120
0"
0%
#125
1!
1$
#127
b111 8
b111 3
b100100001000100000000000000001 2
b11 &
b1100011000110001100000000000 (
b0 *
#130
0!
0$
#135
1"
1%
#137
b101 1
b1 /
b100100001000100000000000000001 .
b111 0
b10000010 -
b1111000 ,
b11 4
b1100011000110001100000000000 5
b0 7
#140
0"
0%
#145
1!
1$
#147
b100100001000100000000000000001 (
b101 *
b1000 8
b1000 3
b11111100000000000000000000000000 2
#150
0!
0$
#155
1"
1%
#157
b100100001000100000000000000001 5
b101 7
b0 /
b11111100000000000000000000000000 .
b1000 0
b0 -
b0 ,
#160
0"
0%
#165
1!
1$
#167
b1001 8
b1001 3
bx 2
b11111100000000000000000000000000 (
1+
